email_processor/__init__.py
email_processor/process_invoices.py
email_invoice_processor-0.1.2.dist-info/METADATA
email_invoice_processor-0.1.2.dist-info/WHEEL
email_invoice_processor-0.1.2.dist-info/entry_points.txt
email_invoice_processor-0.1.2.dist-info/RECORD
