Metadata-Version: 2.3
Name: email-invoice-processor
Version: 0.1.2
Summary: Email invoice processor with OCR capabilities
License: Apache-2.0
Author: Tom Sapletta
Author-email: info@softreck.dev
Requires-Python: >=3.9,<4.0
Classifier: License :: OSI Approved :: Apache Software License
Classifier: Programming Language :: Python :: 3
Classifier: Programming Language :: Python :: 3.9
Classifier: Programming Language :: Python :: 3.10
Classifier: Programming Language :: Python :: 3.11
Classifier: Programming Language :: Python :: 3.12
Classifier: Programming Language :: Python :: 3.13
Requires-Dist: Pillow (>=10.0.0,<11.0.0)
Requires-Dist: email-validator (>=2.0.0,<3.0.0)
Requires-Dist: numpy (>=1.26.0,<2.0.0)
Requires-Dist: opencv-python-headless (>=4.8.0,<5.0.0)
Requires-Dist: pdf2image (>=1.16.3,<2.0.0)
Requires-Dist: pytesseract (>=0.3.10,<0.4.0)
Requires-Dist: python-dateutil (>=2.8.2,<3.0.0)
Requires-Dist: python-dotenv (>=1.0.0,<2.0.0)
Requires-Dist: pyyaml (>=6.0.0,<7.0.0)
